kristall/__init__.py
kristall/_version.py
kristall/application.py
kristall/request.py
kristall/response.py
kristall/utils.py
kristall-0.2.2.dist-info/LICENSE
kristall-0.2.2.dist-info/METADATA
kristall-0.2.2.dist-info/WHEEL
kristall-0.2.2.dist-info/top_level.txt
kristall-0.2.2.dist-info/RECORD
